Vision_Tools-0.2.0.data/scripts/vision
vapi/ActionLabels.py
vapi/ActionTags.py
vapi/Categories.py
vapi/ConnectionDevices.py
vapi/Datasets.py
vapi/DeployedModels.py
vapi/Dltasks.py
vapi/DnnScripts.py
vapi/FileUserKeys.py
vapi/FileUserMetadata.py
vapi/Files.py
vapi/InferenceResults.py
vapi/ObjectTags.py
vapi/Objectlabels.py
vapi/TrainedModels.py
vapi/Users.py
vapi/__init__.py
vapi/base.py
vapi/projects.py
vapi/server.py
vapi_cli/__init__.py
vapi_cli/categories.py
vapi_cli/cli_utils.py
vapi_cli/datasets.py
vapi_cli/deployed-models.py
vapi_cli/dltasks.py
vapi_cli/docopt.py
vapi_cli/files.py
vapi_cli/fkeys.py
vapi_cli/fmetadata.py
vapi_cli/object-labels.py
vapi_cli/object-tags.py
vapi_cli/projects.py
vapi_cli/trained-models.py
vapi_cli/users.py
Vision_Tools-0.2.0.dist-info/LICENSE
Vision_Tools-0.2.0.dist-info/METADATA
Vision_Tools-0.2.0.dist-info/WHEEL
Vision_Tools-0.2.0.dist-info/top_level.txt
Vision_Tools-0.2.0.dist-info/RECORD
