Metadata-Version: 2.1
Name: Vision-Tools
Version: 0.2.0
Summary: Tools to interface with an IBM Visual Inspection server's ReST API.
Home-page: https://github.com/ibm/vision-tools
Author: Carl Bender
Author-email: bcarl@us.ibm.com
License: UNKNOWN
Platform: UNKNOWN
Classifier: Programming Language :: Python :: 3
Classifier: License :: OSI Approved :: Apache Software License
Classifier: Operating System :: OS Independent
Requires-Python: >=3.6
Requires-Dist: requests
